Perimetr/__init__.py
Perimetr/monitor.py
Perimetr-0.0.3.dist-info/LICENSE
Perimetr-0.0.3.dist-info/METADATA
Perimetr-0.0.3.dist-info/WHEEL
Perimetr-0.0.3.dist-info/top_level.txt
Perimetr-0.0.3.dist-info/RECORD
