Metadata-Version: 2.1
Name: Perimetr
Version: 0.0.3
Summary: A dead hand system that monitor changes in network device and act accordingly
Home-page: https://github.com/TonyCSB/Perimetr
Author: Tony Chen
Author-email: github@tonychen.page
License: UNKNOWN
Project-URL: Bug Tracker, https://github.com/TonyCSB/Perimetr/issues
Platform: UNKNOWN
Classifier: Programming Language :: Python :: 3
Classifier: License :: OSI Approved :: GNU General Public License v3 (GPLv3)
Classifier: Operating System :: OS Independent
Requires-Python: >=3.6
License-File: LICENSE
